f_scheduler/__init__.py
f_scheduler/modules/__init__.py
f_scheduler/modules/dag.py
f_scheduler/operators/__init__.py
f_scheduler/operators/base_op.py
f_scheduler/operators/condition_op.py
f_scheduler/operators/function_op.py
f_scheduler/operators/iter_function_op.py
f_scheduler/utils/__init__.py
f_scheduler/utils/converter.py
f_scheduler-0.4.0.dist-info/LICENSE
f_scheduler-0.4.0.dist-info/METADATA
f_scheduler-0.4.0.dist-info/WHEEL
f_scheduler-0.4.0.dist-info/top_level.txt
f_scheduler-0.4.0.dist-info/RECORD
