Metadata-Version: 2.1
Name: f-scheduler
Version: 0.4.0
Summary: Simplify Function Scheduler with Python 3
Author-email: minwook-shin <minwook0106@gmail.com>
Project-URL: Homepage, https://github.com/minwook-shin/f-scheduler
Project-URL: Bug Tracker, https://github.com/minwook-shin/f-scheduler/issues
Classifier: Programming Language :: Python :: 3
Classifier: License :: OSI Approved :: Apache Software License
Classifier: Operating System :: OS Independent
Requires-Python: >=3.9
License-File: LICENSE
Provides-Extra: dev
Requires-Dist: build ==1.1.1 ; extra == 'dev'
